<?xml version="1.0" encoding="UTF-8"?>
<vivadoHLSLog:LogRoot xmlns:vivadoHLSLog="www.xilinx.com/vivadoHLSLog">
  <errorLogs>
    <logs>
      <synLog/>
    </logs>
  </errorLogs>
  <warningLogs>
    <logs>
      <synLog>
        <logs message="WARNING: [RTGEN 206-101] Register 'hcal_cluster_hls_ap_uint_ap_uint_ap_uint_stream_stream_stream_stream_4_a_24' is power-on initialization." projectName="GEp_trigger" solutionName="solution1" date="2024-01-09T15:59:07.891-0500" type="Warning"/>
        <logs message="WARNING: [RTGEN 206-101] Register 'hcal_cluster_hls_ap_uint_ap_uint_ap_uint_stream_stream_stream_stream_4_a_25' is power-on initialization." projectName="GEp_trigger" solutionName="solution1" date="2024-01-09T15:59:07.114-0500" type="Warning"/>
        <logs message="WARNING: [RTGEN 206-101] Register 'hcal_cluster_hls_ap_uint_ap_uint_ap_uint_stream_stream_stream_stream_4_a_7' is power-on initialization." projectName="GEp_trigger" solutionName="solution1" date="2024-01-09T15:59:07.106-0500" type="Warning"/>
        <logs message="WARNING: [RTGEN 206-101] Register 'hcal_cluster_hls_ap_uint_ap_uint_ap_uint_stream_stream_stream_stream_4_a_8' is power-on initialization." projectName="GEp_trigger" solutionName="solution1" date="2024-01-09T15:59:07.100-0500" type="Warning"/>
        <logs message="WARNING: [RTGEN 206-101] Register 'p_ZZ16hcal_cluster_hls7ap_uintILi3EES_ILi13EES_ILi16EERN3hls6streamI13fadc_hits_v_38' is power-on initialization." projectName="GEp_trigger" solutionName="solution1" date="2024-01-09T15:59:07.095-0500" type="Warning"/>
        <logs message="WARNING: [RTGEN 206-101] Register 'p_ZZ16hcal_cluster_hls7ap_uintILi3EES_ILi13EES_ILi16EERN3hls6streamI13fadc_hits_v_39' is power-on initialization." projectName="GEp_trigger" solutionName="solution1" date="2024-01-09T15:59:07.089-0500" type="Warning"/>
        <logs message="WARNING: [RTGEN 206-101] Register 'p_ZZ16hcal_cluster_hls7ap_uintILi3EES_ILi13EES_ILi16EERN3hls6streamI13fadc_hits_v_18' is power-on initialization." projectName="GEp_trigger" solutionName="solution1" date="2024-01-09T15:59:07.085-0500" type="Warning"/>
      </synLog>
    </logs>
  </warningLogs>
</vivadoHLSLog:LogRoot>
